example_scripts/__init__.py
example_scripts/compute_ant_pat_lpf_psd.py
example_scripts/generate_lambdified_functions.py
example_scripts/legacy_multi_network_example.py
example_scripts/multi_network_gw_benchmarking.py
example_scripts/single_network_gw_bencharking.py
example_scripts/test_run.py
example_scripts/use_simualtor.py
gwbench/__init__.py
gwbench/analytic_derivatives.py
gwbench/antenna_pattern_jx.py
gwbench/antenna_pattern_np.py
gwbench/antenna_pattern_sp.py
gwbench/basic_relations.py
gwbench/detector.py
gwbench/detector_response_derivatives.py
gwbench/err_deriv_handling.py
gwbench/fisher_analysis_tools.py
gwbench/injections.py
gwbench/legacy.py
gwbench/multi_network.py
gwbench/network.py
gwbench/psd.py
gwbench/simulator.py
gwbench/snr.py
gwbench/utils.py
gwbench/waveform.py
gwbench/wf_derivatives_num.py
gwbench/wf_derivatives_sym.py
gwbench/noise_curves/CE20km_1p0MW_Aplus_coat_strain.txt
gwbench/noise_curves/CE20km_1p0MW_aLIGO_coat_strain.txt
gwbench/noise_curves/CE20km_1p5MW_Aplus_coat_strain.txt
gwbench/noise_curves/CE20km_1p5MW_aLIGO_coat_strain.txt
gwbench/noise_curves/CE40km_1p0MW_Aplus_coat_strain.txt
gwbench/noise_curves/CE40km_1p0MW_aLIGO_coat_strain.txt
gwbench/noise_curves/CE40km_1p5MW_Aplus_coat_strain.txt
gwbench/noise_curves/CE40km_1p5MW_aLIGO_coat_strain.txt
gwbench/noise_curves/__init__.py
gwbench/noise_curves/a_plus.txt
gwbench/noise_curves/a_sharp.txt
gwbench/noise_curves/advirgo_plus.txt
gwbench/noise_curves/ce1_10km_cb.txt
gwbench/noise_curves/ce1_10km_pm.txt
gwbench/noise_curves/ce1_20km_cb.txt
gwbench/noise_curves/ce1_20km_pm.txt
gwbench/noise_curves/ce1_30km_cb.txt
gwbench/noise_curves/ce1_30km_pm.txt
gwbench/noise_curves/ce1_40km_cb.txt
gwbench/noise_curves/ce1_40km_pm.txt
gwbench/noise_curves/ce2_10km_cb.txt
gwbench/noise_curves/ce2_10km_pm.txt
gwbench/noise_curves/ce2_20km_cb.txt
gwbench/noise_curves/ce2_20km_pm.txt
gwbench/noise_curves/ce2_30km_cb.txt
gwbench/noise_curves/ce2_30km_pm.txt
gwbench/noise_curves/ce2_40km_cb.txt
gwbench-0.8.9.dist-info/licenses/AUTHORS.md
gwbench-0.8.9.dist-info/licenses/LICENSE
gwbench-0.8.9.dist-info/METADATA
gwbench-0.8.9.dist-info/WHEEL
gwbench-0.8.9.dist-info/top_level.txt
gwbench-0.8.9.dist-info/RECORD
