Metadata-Version: 2.4
Name: gwbench
Version: 0.8.9
Summary: A small tool to benchmark GW events
Home-page: https://gitlab.com/sborhanian/gwbench
Author: Ssohrab Borhanian
Author-email: sborhanian@gmail.com
Classifier: Programming Language :: Python :: 3
Requires-Python: >=3.9
License-File: LICENSE
License-File: AUTHORS.md
Dynamic: author
Dynamic: author-email
Dynamic: classifier
Dynamic: home-page
Dynamic: license-file
Dynamic: requires-python
Dynamic: summary
